{"ok":true,"source":"Weerstation_BP","device":"esp32","timestamp_ms":1539050825,"temperatuur_c":22.07,"luchtvochtigheid_percent":75.94,"luchtdruk_pa":102100.00,"luchtdruk_hpa":1021.00,"felheid_zon_lux":87320.00,"wind":{"snelheid_m_s":3.80,"snelheid_min_m_s":2.30,"snelheid_max_m_s":5.20,"richting_graden":358.60,"richting_min_graden":0.90,"richting_max_graden":358.80},"regen":{"totaal_mm":852.40,"duur_s":24570.00,"intensiteit_mm_h":0.40,"max_intensiteit_mm_h":12.00},"zon":{"licht_lux":87320.00,"straling_w_m2":0.00,"zonneschijn_duur_h":0.00},"luchtkwaliteit":{"pm25_ug_m3":0.00,"pm10_ug_m3":0.00,"co2_ppm":0.00,"geluid_db":0.00},"heater_temperatuur_c":22.34,"tilt_state": 0,"weergave_":{"temperatuur_c":22.07,"windkracht_bft":3,"windkracht_omschrijving":"matige wind","windrichting":"noorden","zon_status":"zonnig"}}