{"ok":true,"source":"Weerstation_BP","device":"esp32","timestamp_ms":11178604,"temperatuur_c":13.84,"luchtvochtigheid_percent":67.95,"luchtdruk_pa":101080.00,"luchtdruk_hpa":1010.80,"felheid_zon_lux":50165.00,"wind":{"snelheid_m_s":4.70,"snelheid_min_m_s":3.00,"snelheid_max_m_s":6.80,"richting_graden":358.70,"richting_min_graden":1.20,"richting_max_graden":359.30},"regen":{"totaal_mm":6.60,"duur_s":330.00,"intensiteit_mm_h":0.00,"max_intensiteit_mm_h":0.00},"zon":{"licht_lux":50165.00,"straling_w_m2":0.00,"zonneschijn_duur_h":0.00},"luchtkwaliteit":{"pm25_ug_m3":0.00,"pm10_ug_m3":0.00,"co2_ppm":0.00,"geluid_db":0.00},"heater_temperatuur_c":15.09,"tilt_state": 0}